Workbook

Sheet Exp
A1: NEXT MEDIA
A2: PLOT 13, SUMMIT VIEW ROAD
A3: P.O BOX 7613
A4: EXPENSE ALLOWANCES FOR THE MONTH ENDED 15 JULY, 2026 | E4: .
B7: Name | C7: Position | D7: Expense Allowance | E7: SACCO | F7: Food | G7: Medicare | H7: Hire purchase | I7: Cost share | J7: ID Replacement | K7: Fuel/Advance | L7: Net Expense Allowance
A8: 1 | B8: Aaron Magulu | C8: Stores | L8: =D8-E8-F8-G8-H8-I8-J8-K8 -> 0 | M8: =E8+F8+G8+H8+I8+J8+K8+L8 -> 0 | N8: =D8-M8 -> 0
A9: 2 | B9: Abdallah Gulemye | C9: Content Officer | L9: =D9-E9-F9-G9-H9-I9-J9-K9 -> 0 | M9: =E9+F9+G9+H9+I9+J9+K9+L9 -> 0 | N9: =D9-M9 -> 0
A10: 3 | B10: Abdallah Magumba | C10: Current Affairs Director | L10: =D10-E10-F10-G10-H10-I10-J10-K10 -> 0 | M10: =E10+F10+G10+H10+I10+J10+K10+L10 -> 0 | N10: =D10-M10 -> 0
A11: 4 | B11: Abdul Majid Mugisa | C11: Content Officer | L11: =D11-E11-F11-G11-H11-I11-J11-K11 -> 0 | M11: =E11+F11+G11+H11+I11+J11+K11+L11 -> 0 | N11: =D11-M11 -> 0
A12: 5 | B12: Abubaker Lubwama | C12: SM Resources | L12: =D12-E12-F12-G12-H12-I12-J12-K12 -> 0 | M12: =E12+F12+G12+H12+I12+J12+K12+L12 -> 0 | N12: =D12-M12 -> 0
A13: 6 | B13: Adam Mayambala | C13: News Reporter | L13: =D13-E13-F13-G13-H13-I13-J13-K13 -> 0 | M13: =E13+F13+G13+H13+I13+J13+K13+L13 -> 0 | N13: =D13-M13 -> 0
A14: 7 | B14: Adrian Bakuwama | C14: Content Officer | L14: =D14-E14-F14-G14-H14-I14-J14-K14 -> 0 | M14: =E14+F14+G14+H14+I14+J14+K14+L14 -> 0 | N14: =D14-M14 -> 0
A15: 8 | B15: Aggrey Waguma | C15: Studio Cameraperson | L15: =D15-E15-F15-G15-H15-I15-J15-K15 -> 0 | M15: =E15+F15+G15+H15+I15+J15+K15+L15 -> 0 | N15: =D15-M15 -> 0
A16: 9 | B16: Ahmed Sultan Buyungo | C16: Video Editor/Producer | L16: =D16-E16-F16-G16-H16-I16-J16-K16 -> 0 | M16: =E16+F16+G16+H16+I16+J16+K16+L16 -> 0 | N16: =D16-M16 -> 0
A17: 10 | B17: Aisha Komugisha | C17: Payable Accountant | L17: =D17-E17-F17-G17-H17-I17-J17-K17 -> 0 | M17: =E17+F17+G17+H17+I17+J17+K17+L17 -> 0 | N17: =D17-M17 -> 0
A18: 11 | B18: Alex Mugasha | C18: Bureau Chief-Mbarara | L18: =D18-E18-F18-G18-H18-I18-J18-K18 -> 0 | M18: =E18+F18+G18+H18+I18+J18+K18+L18 -> 0 | N18: =D18-M18 -> 0
A19: 12 | B19: Alex Ssentongo | C19: Video Editor | L19: =D19-E19-F19-G19-H19-I19-J19-K19 -> 0 | M19: =E19+F19+G19+H19+I19+J19+K19+L19 -> 0 | N19: =D19-M19 -> 0
... A26: 19 | B26: Baker Zenah | C26: Head of Content Production | L26: =D26-E26-F26-G26-H26-I26-J26-K26 -> 0 | M26: =E26+F26+G26+H26+I26+J26+K26+L26 -> 0 | N26: =D26-M26 -> 0
A27: 20 | B27: Balinda Immam | L27: =D27-E27-F27-G27-H27-I27-J27-K27 -> 0 | M27: =E27+F27+G27+H27+I27+J27+K27+L27 -> 0 | N27: =D27-M27 -> 0
A28: 21 | B28: Ben Mwine | C28: HOC&P | L28: =D28-E28-F28-G28-H28-I28-J28-K28 -> 0 | M28: =E28+F28+G28+H28+I28+J28+K28+L28 -> 0 | N28: =D28-M28 -> 0
A29: 22 | B29: Benson Ongom | C29: Bureau Chief | L29: =D29-E29-F29-G29-H29-I29-J29-K29 -> 0 | M29: =E29+F29+G29+H29+I29+J29+K29+L29 -> 0 | N29: =D29-M29 -> 0
A30: 23 | B30: Betty Kayenga | C30: Payable Accountant | L30: =D30-E30-F30-G30-H30-I30-J30-K30 -> 0 | M30: =E30+F30+G30+H30+I30+J30+K30+L30 -> 0 | N30: =D30-M30 -> 0
A31: 24 | B31: Boman Bigirwenkya | C31: Head of Finance | L31: =D31-E31-F31-G31-H31-I31-J31-K31 -> 0 | M31: =E31+F31+G31+H31+I31+J31+K31+L31 -> 0 | N31: =D31-M31 -> 0
A32: 25 | B32: Bosco Afasha | C32: Driver | L32: =D32-E32-F32-G32-H32-I32-J32-K32 -> 0 | M32: =E32+F32+G32+H32+I32+J32+K32+L32 -> 0 | N32: =D32-M32 -> 0
A33: 26 | B33: Bridget Nsimenta | C33: Bureau Reporter- Mbarara | L33: =D33-E33-F33-G33-H33-I33-J33-K33 -> 0 | M33: =E33+F33+G33+H33+I33+J33+K33+L33 -> 0 | N33: =D33-M33 -> 0
A34: 27 | B34: Calvin Mugume | C34: CFO | L34: =D34-E34-F34-G34-H34-I34-J34-K34 -> 0 | M34: =E34+F34+G34+H34+I34+J34+K34+L34 -> 0 | N34: =D34-M34 -> 0
A35: 28 | B35: Canary Mugume | C35: News Anchor | L35: =D35-E35-F35-G35-H35-I35-J35-K35 -> 0 | M35: =E35+F35+G35+H35+I35+J35+K35+L35 -> 0 | N35: =D35-M35 -> 0
A36: 29 | B36: Catherine Nakato | C36: Reporter | L36: =D36-E36-F36-G36-H36-I36-J36-K36 -> 0 | M36: =E36+F36+G36+H36+I36+J36+K36+L36 -> 0 | N36: =D36-M36 -> 0
A37: 30 | B37: Crish Semanda | L37: =D37-E37-F37-G37-H37-I37-J37-K37 -> 0 | M37: =E37+F37+G37+H37+I37+J37+K37+L37 -> 0 | N37: =D37-M37 -> 0
A38: 31 | B38: Christopher Lutwama | C38: Content Manager Officer | L38: =D38-E38-F38-G38-H38-I38-J38-K38 -> 0 | M38: =E38+F38+G38+H38+I38+J38+K38+L38 -> 0 | N38: =D38-M38 -> 0
A39: 32 | B39: Christopher Wanobere | C39: GM Broadcast | L39: =D39-E39-F39-G39-H39-I39-J39-K39 -> 0 | M39: =E39+F39+G39+H39+I39+J39+K39+L39 -> 0 | N39: =D39-M39 -> 0
A40: 33 | B40: Dalton Kaweesa | C40: Head of Current Affairs | L40: =D40-E40-F40-G40-H40-I40-J40-K40 -> 0 | M40: =E40+F40+G40+H40+I40+J40+K40+L40 -> 0 | N40: =D40-M40 -> 0
A41: 34 | B41: Dan Ayebare | C41: News Reporter | L41: =D41-E41-F41-G41-H41-I41-J41-K41 -> 0 | M41: =E41+F41+G41+H41+I41+J41+K41+L41 -> 0 | N41: =D41-M41 -> 0
A42: 35 | B42: David Ochieng | C42: Bureau Chief - Bukedi | L42: =D42-E42-F42-G42-H42-I42-J42-K42 -> 0 | M42: =E42+F42+G42+H42+I42+J42+K42+L42 -> 0 | N42: =D42-M42 -> 0
A43: 36 | B43: Dennis Ibanda Mugulusi | C43: Cameraperson | L43: =D43-E43-F43-G43-H43-I43-J43-K43 -> 0 | M43: =E43+F43+G43+H43+I43+J43+K43+L43 -> 0 | N43: =D43-M43 -> 0
A44: 37 | B44: Derrick Kyambadde | C44: Video Editor | L44: =D44-E44-F44-G44-H44-I44-J44-K44 -> 0 | M44: =E44+F44+G44+H44+I44+J44+K44+L44 -> 0 | N44: =D44-M44 -> 0
A45: 38 | B45: Derrick Ssemwogerere henry | C45: Studio Cameraperson | L45: =D45-E45-F45-G45-H45-I45-J45-K45 -> 0 | M45: =E45+F45+G45+H45+I45+J45+K45+L45 -> 0 | N45: =D45-M45 -> 0
A46: 39 | B46: Desire Derekford Mugumisa | C46: HOCA | L46: =D46-E46-F46-G46-H46-I46-J46-K46 -> 0 | M46: =E46+F46+G46+H46+I46+J46+K46+L46 -> 0 | N46: =D46-M46 -> 0
A47: 40 | B47: Dorah Atwongyeire | C47: Head of Multi media | L47: =D47-E47-F47-G47-H47-I47-J47-K47 -> 0 | M47: =E47+F47+G47+H47+I47+J47+K47+L47 -> 0 | N47: =D47-M47 -> 0
A48: 41 | B48: Edgar Mathew Karuhanga | C48: News Reporter | L48: =D48-E48-F48-G48-H48-I48-J48-K48 -> 0 | M48: =E48+F48+G48+H48+I48+J48+K48+L48 -> 0 | N48: =D48-M48 -> 0
A49: 42 | B49: Emmanuel Ojok Otim | C49: Cameraperson | L49: =D49-E49-F49-G49-H49-I49-J49-K49 -> 0 | M49: =E49+F49+G49+H49+I49+J49+K49+L49 -> 0 | N49: =D49-M49 -> 0
... A53: 46 | B53: Esther Birungi | C53: Producer | L53: =D53-E53-F53-G53-H53-I53-J53-K53 -> 0 | M53: =E53+F53+G53+H53+I53+J53+K53+L53 -> 0 | N53: =D53-M53 -> 0
A54: 47 | B54: Fadhil Mahad | L54: =D54-E54-F54-G54-H54-I54-J54-K54 -> 0 | M54: =E54+F54+G54+H54+I54+J54+K54+L54 -> 0 | N54: =D54-M54 -> 0
A55: 48 | B55: Fahad Tenywa | L55: =D55-E55-F55-G55-H55-I55-J55-K55 -> 0 | M55: =E55+F55+G55+H55+I55+J55+K55+L55 -> 0 | N55: =D55-M55 -> 0
A56: 49 | B56: Farish Magembe | C56: Bureau Chief - Masaka | L56: =D56-E56-F56-G56-H56-I56-J56-K56 -> 0 | M56: =E56+F56+G56+H56+I56+J56+K56+L56 -> 0 | N56: =D56-M56 -> 0
A57: 50 | B57: Ferdinand Sekiganda | C57: Legal Officer | L57: =D57-E57-F57-G57-H57-I57-J57-K57 -> 0 | M57: =E57+F57+G57+H57+I57+J57+K57+L57 -> 0 | N57: =D57-M57 -> 0
A58: 51 | B58: Francis Isaano | C58: Photographer | L58: =D58-E58-F58-G58-H58-I58-J58-K58 -> 0 | M58: =E58+F58+G58+H58+I58+J58+K58+L58 -> 0 | N58: =D58-M58 -> 0
A59: 52 | B59: Francis Kasozi | C59: Transmission Operator | L59: =D59-E59-F59-G59-H59-I59-J59-K59 -> 0 | M59: =E59+F59+G59+H59+I59+J59+K59+L59 -> 0 | N59: =D59-M59 -> 0
A60: 53 | B60: Francis Mutambuka | C60: Fleet manager | L60: =D60-E60-F60-G60-H60-I60-J60-K60 -> 0 | M60: =E60+F60+G60+H60+I60+J60+K60+L60 -> 0 | N60: =D60-M60 -> 0
A61: 54 | B61: Fredrick Lutakome | C61: Cameraperson | L61: =D61-E61-F61-G61-H61-I61-J61-K61 -> 0 | M61: =E61+F61+G61+H61+I61+J61+K61+L61 -> 0 | N61: =D61-M61 -> 0
A62: 55 | B62: Geofrey Ssenyondo | C62: Video Editor | L62: =D62-E62-F62-G62-H62-I62-J62-K62 -> 0 | M62: =E62+F62+G62+H62+I62+J62+K62+L62 -> 0 | N62: =D62-M62 -> 0
A63: 56 | B63: Gerald Matembu | C63: Bureau Chief- Bugisu | L63: =D63-E63-F63-G63-H63-I63-J63-K63 -> 0 | M63: =E63+F63+G63+H63+I63+J63+K63+L63 -> 0 | N63: =D63-M63 -> 0
A64: 57 | B64: Greggy Busolo | C64: Head of Operations | L64: =D64-E64-F64-G64-H64-I64-J64-K64 -> 0 | M64: =E64+F64+G64+H64+I64+J64+K64+L64 -> 0 | N64: =D64-M64 -> 0
A65: 58 | B65: Gloria Nambi | C65: Business Data Analyst | L65: =D65-E65-F65-G65-H65-I65-J65-K65 -> 0 | M65: =E65+F65+G65+H65+I65+J65+K65+L65 -> 0 | N65: =D65-M65 -> 0
A66: 59 | B66: Goretti Kyeswa | C66: SM Editorial Advisory | L66: =D66-E66-F66-G66-H66-I66-J66-K66 -> 0 | M66: =E66+F66+G66+H66+I66+J66+K66+L66 -> 0 | N66: =D66-M66 -> 0
A67: 60 | B67: Gorret Nakalinzi | C67: Tax Accountant | L67: =D67-E67-F67-G67-H67-I67-J67-K67 -> 0 | M67: =E67+F67+G67+H67+I67+J67+K67+L67 -> 0 | N67: =D67-M67 -> 0
... A91: 84 | B91: Jean Francis Ssemanda | C91: Cameraperson | L91: =D91-E91-F91-G91-H91-I91-J91-K91 -> 0 | M91: =E91+F91+G91+H91+I91+J91+K91+L91 -> 0 | N91: =D91-M91 -> 0
A92: 85 | B92: Jimmy Okech | L92: =D92-E92-F92-G92-H92-I92-J92-K92 -> 0 | M92: =E92+F92+G92+H92+I92+J92+K92+L92 -> 0 | N92: =D92-M92 -> 0
A93: 86 | B93: John Paul Kiwanuka | C93: Cameraperson | L93: =D93-E93-F93-G93-H93-I93-J93-K93 -> 0 | M93: =E93+F93+G93+H93+I93+J93+K93+L93 -> 0 | N93: =D93-M93 -> 0
A94: 87 | B94: Joseph Makumbi | C94: Cameraperson | L94: =D94-E94-F94-G94-H94-I94-J94-K94 -> 0 | M94: =E94+F94+G94+H94+I94+J94+K94+L94 -> 0 | N94: =D94-M94 -> 0
A95: 88 | B95: Joseph Mawanda | C95: Driver | L95: =D95-E95-F95-G95-H95-I95-J95-K95 -> 0 | M95: =E95+F95+G95+H95+I95+J95+K95+L95 -> 0 | N95: =D95-M95 -> 0
A96: 89 | B96: Joseph Omagor | C96: Bureau chief Gulu | L96: =D96-E96-F96-G96-H96-I96-J96-K96 -> 0 | M96: =E96+F96+G96+H96+I96+J96+K96+L96 -> 0 | N96: =D96-M96 -> 0
A97: 90 | B97: Joseph Rwanguhayo | C97: Cameraperson | L97: =D97-E97-F97-G97-H97-I97-J97-K97 -> 0 | M97: =E97+F97+G97+H97+I97+J97+K97+L97 -> 0 | N97: =D97-M97 -> 0
A98: 91 | B98: Josephat Walugembe | C98: News Producer/Anchor | L98: =D98-E98-F98-G98-H98-I98-J98-K98 -> 0 | M98: =E98+F98+G98+H98+I98+J98+K98+L98 -> 0 | N98: =D98-M98 -> 0
A99: 92 | B99: Joshua Kakeeto | C99: Cameraperson | L99: =D99-E99-F99-G99-H99-I99-J99-K99 -> 0 | M99: =E99+F99+G99+H99+I99+J99+K99+L99 -> 0 | N99: =D99-M99 -> 0
A100: 93 | B100: Joshua Mujunga | C100: Video Journalist | L100: =D100-E100-F100-G100-H100-I100-J100-K100 -> 0 | M100: =E100+F100+G100+H100+I100+J100+K100+L100 -> 0 | N100: =D100-M100 -> 0
A101: 94 | B101: Joshua Rwamura | C101: Cameraperson | L101: =D101-E101-F101-G101-H101-I101-J101-K101 -> 0 | M101: =E101+F101+G101+H101+I101+J101+K101+L101 -> 0 | N101: =D101-M101 -> 0
A102: 95 | B102: Joshua Wavamuno | L102: =D102-E102-F102-G102-H102-I102-J102-K102 -> 0 | M102: =E102+F102+G102+H102+I102+J102+K102+L102 -> 0 | N102: =D102-M102 -> 0
A103: 96 | B103: Juliet Mbabazi | C103: SM Client Relations | L103: =D103-E103-F103-G103-H103-I103-J103-K103 -> 0 | M103: =E103+F103+G103+H103+I103+J103+K103+L103 -> 0 | N103: =D103-M103 -> 0
A104: 97 | B104: Julius Yiga Bakabaage | C104: Video Journaist | L104: =D104-E104-F104-G104-H104-I104-J104-K104 -> 0 | M104: =E104+F104+G104+H104+I104+J104+K104+L104 -> 0 | N104: =D104-M104 -> 0
A105: 98 | B105: Katagwa George | C105: Camera Man | L105: =D105-E105-F105-G105-H105-I105-J105-K105 -> 0 | M105: =E105+F105+G105+H105+I105+J105+K105+L105 -> 0 | N105: =D105-M105 -> 0
A106: 99 | B106: Katumba Moses | C106: Driver | L106: =D106-E106-F106-G106-H106-I106-J106-K106 -> 0 | M106: =E106+F106+G106+H106+I106+J106+K106+L106 -> 0 | N106: =D106-M106 -> 0
A107: 100 | B107: Kaudha Mwasit | C107: Asst. Admin | L107: =D107-E107-F107-G107-H107-I107-J107-K107 -> 0 | M107: =E107+F107+G107+H107+I107+J107+K107+L107 -> 0 | N107: =D107-M107 -> 0
A108: 101 | B108: Kenneth Kaweesa | C108: Reporter | L108: =D108-E108-F108-G108-H108-I108-J108-K108 -> 0 | M108: =E108+F108+G108+H108+I108+J108+K108+L108 -> 0 | N108: =D108-M108 -> 0
A109: 102 | B109: Kin Ibrahim Kariisa | C109: CEO | L109: =D109-E109-F109-G109-H109-I109-J109-K109 -> 0 | M109: =E109+F109+G109+H109+I109+J109+K109+L109 -> 0 | N109: =D109-M109 -> 0
A110: 103 | B110: Kitimbo Thomas | C110: Camera Man | L110: =D110-E110-F110-G110-H110-I110-J110-K110 -> 0 | M110: =E110+F110+G110+H110+I110+J110+K110+L110 -> 0 | N110: =D110-M110 -> 0
A111: 104 | B111: Lawrence Mushabe | L111: =D111-E111-F111-G111-H111-I111-J111-K111 -> 0 | M111: =E111+F111+G111+H111+I111+J111+K111+L111 -> 0 | N111: =D111-M111 -> 0
A112: 105 | B112: Leila Nalukwata | C112: Audit Ass | L112: =D112-E112-F112-G112-H112-I112-J112-K112 -> 0 | M112: =E112+F112+G112+H112+I112+J112+K112+L112 -> 0 | N112: =D112-M112 -> 0
A113: 106 | B113: Levi Muhoozi | C113: Brand Manager | L113: =D113-E113-F113-G113-H113-I113-J113-K113 -> 0 | M113: =E113+F113+G113+H113+I113+J113+K113+L113 -> 0 | N113: =D113-M113 -> 0
A114: 107 | B114: Lilian Mutesi | C114: Chief of Staff | L114: =D114-E114-F114-G114-H114-I114-J114-K114 -> 0 | M114: =E114+F114+G114+H114+I114+J114+K114+L114 -> 0 | N114: =D114-M114 -> 0
A115: 108 | B115: Lotus Martha Kugonza | C115: Producer | L115: =D115-E115-F115-G115-H115-I115-J115-K115 -> 0 | M115: =E115+F115+G115+H115+I115+J115+K115+L115 -> 0 | N115: =D115-M115 -> 0
A116: 109 | B116: Lukwago Emmanuel | C116: In-House DJ | L116: =D116-E116-F116-G116-H116-I116-J116-K116 -> 0 | M116: =E116+F116+G116+H116+I116+J116+K116+L116 -> 0 | N116: =D116-M116 -> 0
A117: 110 | B117: Lydia Nabakooza | C117: News Reporter | L117: =D117-E117-F117-G117-H117-I117-J117-K117 -> 0 | M117: =E117+F117+G117+H117+I117+J117+K117+L117 -> 0 | N117: =D117-M117 -> 0
A118: 111 | B118: Maclean Atuhaire | C118: Client Relations | L118: =D118-E118-F118-G118-H118-I118-J118-K118 -> 0 | M118: =E118+F118+G118+H118+I118+J118+K118+L118 -> 0 | N118: =D118-M118 -> 0
A119: 112 | B119: Marcel Obongonyinge | C119: Head Comm Broadcast | L119: =D119-E119-F119-G119-H119-I119-J119-K119 -> 0 | M119: =E119+F119+G119+H119+I119+J119+K119+L119 -> 0 | N119: =D119-M119 -> 0
A120: 113 | B120: Mariam Kaliisa | C120: Head of Human Capital | L120: =D120-E120-F120-G120-H120-I120-J120-K120 -> 0 | M120: =E120+F120+G120+H120+I120+J120+K120+L120 -> 0 | N120: =D120-M120 -> 0
A121: 114 | B121: Mark Agaba | C121: Protocal | L121: =D121-E121-F121-G121-H121-I121-J121-K121 -> 0 | M121: =E121+F121+G121+H121+I121+J121+K121+L121 -> 0 | N121: =D121-M121 -> 0
A122: 115 | B122: Martha Namutebi | C122: Editor | L122: =D122-E122-F122-G122-H122-I122-J122-K122 -> 0 | M122: =E122+F122+G122+H122+I122+J122+K122+L122 -> 0 | N122: =D122-M122 -> 0
A123: 116 | B123: Martin Kisaamu | C123: Cameraman | L123: =D123-E123-F123-G123-H123-I123-J123-K123 -> 0 | M123: =E123+F123+G123+H123+I123+J123+K123+L123 -> 0 | N123: =D123-M123 -> 0
... A175: 169 | B175: Zawadi Kaliisa | C175: Treasury Manager | L175: =D175-E175-F175-G175-H175-I175-J175-K175 -> 0 | M175: =E175+F175+G175+H175+I175+J175+K175+L175 -> 0 | N175: =D175-M175 -> 0
A176: 170 | L176: =D176-E176-F176-G176-H176-I176-J176-K176 -> 0 | M176: =E176+F176+G176+H176+I176+J176+K176+L176 -> 0 | N176: =D176-M176 -> 0
A177: 171 | L177: =D177-E177-F177-G177-H177-I177-J177-K177 -> 0 | M177: =E177+F177+G177+H177+I177+J177+K177+L177 -> 0 | N177: =D177-M177 -> 0
A178: 172 | B178: NBS SPORT | L178: =D178-E178-F178-G178-H178-I178-J178-K178 -> 0 | M178: =E178+F178+G178+H178+I178+J178+K178+L178 -> 0 | N178: =D178-M178 -> 0
A179: 173 | B179: Ahab Bwesige | C179: Sports Producer | L179: =D179-E179-F179-G179-H179-I179-J179-K179 -> 0 | M179: =E179+F179+G179+H179+I179+J179+K179+L179 -> 0 | N179: =D179-M179 -> 0
A180: 174 | B180: Allan Damba | L180: =D180-E180-F180-G180-H180-I180-J180-K180 -> 0 | M180: =E180+F180+G180+H180+I180+J180+K180+L180 -> 0 | N180: =D180-M180 -> 0
A181: 175 | B181: Benjamin Jermain Egesa | C181: Show Host | L181: =D181-E181-F181-G181-H181-I181-J181-K181 -> 0 | M181: =E181+F181+G181+H181+I181+J181+K181+L181 -> 0 | N181: =D181-M181 -> 0
A182: 176 | B182: Brian Tukasingura | C182: Show Host | L182: =D182-E182-F182-G182-H182-I182-J182-K182 -> 0 | M182: =E182+F182+G182+H182+I182+J182+K182+L182 -> 0 | N182: =D182-M182 -> 0
A183: 177 | B183: Constant Alii | C183: Sports Producer | L183: =D183-E183-F183-G183-H183-I183-J183-K183 -> 0 | M183: =E183+F183+G183+H183+I183+J183+K183+L183 -> 0 | N183: =D183-M183 -> 0
A184: 178 | B184: David Tumusiime | C184: Sports Producer | L184: =D184-E184-F184-G184-H184-I184-J184-K184 -> 0 | M184: =E184+F184+G184+H184+I184+J184+K184+L184 -> 0 | N184: =D184-M184 -> 0
A185: 179 | B185: Elisha Njawuzi | C185: Driver | L185: =D185-E185-F185-G185-H185-I185-J185-K185 -> 0 | M185: =E185+F185+G185+H185+I185+J185+K185+L185 -> 0 | N185: =D185-M185 -> 0
...

Sheet Salary
B1: NEXT MEDIA
B2: PLOT 13 SUMMIT VIEW ROAD
B3: P.O BOX 7613
B4: PAYROLL FOR THE MONTH ENDED 27 JULY, 2026 | J4: .
A7: ID No | B7: Name | C7: Position | D7: Salary | E7: Gross Pay | F7: PAYE | G7: NSSF 10% | H7: NSSF 5% | I7: Total Deduction | J7: SACCO | K7: Food | L7: Medicare | M7: Hire purchase | N7: Cost share | O7: ID Replacement | P7: Penalty | Q7: Net Pay
B8: NBS
A9: 903/20 | B9: Aaron Magulu | C9: Grip and Stage | Q9: =E9-I9-J9-K9-L9-M9-N9-O9-P9 -> 0 | R9: =J9+K9+L9+M9+N9+O9+P9+Q9 -> 0 | S9: =D9-R9 -> 0
A10: 743/20 | B10: Abdallah Magumba | C10: Transmission | Q10: =E10-I10-J10-K10-L10-M10-N10-O10-P10 -> 0 | R10: =J10+K10+L10+M10+N10+O10+P10+Q10 -> 0 | S10: =D10-R10 -> 0
A11: 714/20 | B11: Abdallar Gulemye | C11: Content Officer | Q11: =E11-I11-J11-K11-L11-M11-N11-O11-P11 -> 0 | R11: =J11+K11+L11+M11+N11+O11+P11+Q11 -> 0 | S11: =D11-R11 -> 0
A12: 769/20 | B12: Abdul Majid Mugisa | C12: Content Officer | Q12: =E12-I12-J12-K12-L12-M12-N12-O12-P12 -> 0 | R12: =J12+K12+L12+M12+N12+O12+P12+Q12 -> 0 | S12: =D12-R12 -> 0
A13: 051/20 | B13: Abubaker Lubwama | C13: Ass Stores | Q13: =E13-I13-J13-K13-L13-M13-N13-O13-P13 -> 0 | R13: =J13+K13+L13+M13+N13+O13+P13+Q13 -> 0 | S13: =D13-R13 -> 0
A14: 683/20 | B14: Adam Mayambala | C14: News Reporter | Q14: =E14-I14-J14-K14-L14-M14-N14-O14-P14 -> 0 | R14: =J14+K14+L14+M14+N14+O14+P14+Q14 -> 0 | S14: =D14-R14 -> 0
A15: 768/20 | B15: Adrian Bakuwamma | C15: Content Officer | Q15: =E15-I15-J15-K15-L15-M15-N15-O15-P15 -> 0 | R15: =J15+K15+L15+M15+N15+O15+P15+Q15 -> 0 | S15: =D15-R15 -> 0
A16: 086/20 | B16: Aggrey Waguma | C16: Camera Man | Q16: =E16-I16-J16-K16-L16-M16-N16-O16-P16 -> 0 | R16: =J16+K16+L16+M16+N16+O16+P16+Q16 -> 0 | S16: =D16-R16 -> 0
A17: 467/20 | B17: Ahmed Sultan Buyungo | C17: Video Editor | Q17: =E17-I17-J17-K17-L17-M17-N17-O17-P17 -> 0 | R17: =J17+K17+L17+M17+N17+O17+P17+Q17 -> 0 | S17: =D17-R17 -> 0
A18: 924/20 | B18: Aisha Komugisha | C18: Payable Accountant | Q18: =E18-I18-J18-K18-L18-M18-N18-O18-P18 -> 0 | R18: =J18+K18+L18+M18+N18+O18+P18+Q18 -> 0 | S18: =D18-R18 -> 0
A19: 710/20 | B19: Alan John Mwesigwa | C19: Bureau chief bunyoro | Q19: =E19-I19-J19-K19-L19-M19-N19-O19-P19 -> 0 | R19: =J19+K19+L19+M19+N19+O19+P19+Q19 -> 0 | S19: =D19-R19 -> 0
A20: 093/20 | B20: Allan Mark Kiberu | C20: Transmission | Q20: =E20-I20-J20-K20-L20-M20-N20-O20-P20 -> 0 | R20: =J20+K20+L20+M20+N20+O20+P20+Q20 -> 0 | S20: =D20-R20 -> 0
... A112: 966/20 | B112: Jimmy Okech | C112: Cameraperson | Q112: =E112-I112-J112-K112-L112-M112-N112-O112-P112 -> 0 | R112: =J112+K112+L112+M112+N112+O112+P112+Q112 -> 0 | S112: =D112-R112 -> 0
B113: Joan Umutesi | C113: Stylist | Q113: =E113-I113-J113-K113-L113-M113-N113-O113-P113 -> 0 | R113: =J113+K113+L113+M113+N113+O113+P113+Q113 -> 0 | S113: =D113-R113 -> 0
A114: 908/20 | B114: Joel Ssali | C114: Tansmission Officer | Q114: =E114-I114-J114-K114-L114-M114-N114-O114-P114 -> 0 | R114: =J114+K114+L114+M114+N114+O114+P114+Q114 -> 0 | S114: =D114-R114 -> 0
A115: 572/20 | B115: John Paul Kiwanuka | C115: Cameraperson | Q115: =E115-I115-J115-K115-L115-M115-N115-O115-P115 -> 0 | R115: =J115+K115+L115+M115+N115+O115+P115+Q115 -> 0 | S115: =D115-R115 -> 0
A116: 463/20 | B116: Joseph Makumbi | C116: Cameraperson | Q116: =E116-I116-J116-K116-L116-M116-N116-O116-P116 -> 0 | R116: =J116+K116+L116+M116+N116+O116+P116+Q116 -> 0 | S116: =D116-R116 -> 0
A117: 197/20 | B117: Joseph Mawanda | C117: Driver | Q117: =E117-I117-J117-K117-L117-M117-N117-O117-P117 -> 0 | R117: =J117+K117+L117+M117+N117+O117+P117+Q117 -> 0 | S117: =D117-R117 -> 0
A118: 709/20 | B118: Joseph Omagor | C118: Bureau chief Gulu | Q118: =E118-I118-J118-K118-L118-M118-N118-O118-P118 -> 0 | R118: =J118+K118+L118+M118+N118+O118+P118+Q118 -> 0 | S118: =D118-R118 -> 0
A119: 388/20 | B119: Joseph Rwanguhayo | C119: Cameraperson | Q119: =E119-I119-J119-K119-L119-M119-N119-O119-P119 -> 0 | R119: =J119+K119+L119+M119+N119+O119+P119+Q119 -> 0 | S119: =D119-R119 -> 0
A120: 198/20 | B120: Joseph Turyagumanawe | C120: Transmission Ass | Q120: =E120-I120-J120-K120-L120-M120-N120-O120-P120 -> 0 | R120: =J120+K120+L120+M120+N120+O120+P120+Q120 -> 0 | S120: =D120-R120 -> 0
A121: 199/20 | B121: Josephat Walugembe | C121: News Producer | Q121: =E121-I121-J121-K121-L121-M121-N121-O121-P121 -> 0 | R121: =J121+K121+L121+M121+N121+O121+P121+Q121 -> 0 | S121: =D121-R121 -> 0
A122: 588/20 | B122: Joshua Kakeeto | C122: Cameraperson | Q122: =E122-I122-J122-K122-L122-M122-N122-O122-P122 -> 0 | R122: =J122+K122+L122+M122+N122+O122+P122+Q122 -> 0 | S122: =D122-R122 -> 0
A123: 201/20 | B123: Joshua Mujunga | C123: Video Journalist | Q123: =E123-I123-J123-K123-L123-M123-N123-O123-P123 -> 0 | R123: =J123+K123+L123+M123+N123+O123+P123+Q123 -> 0 | S123: =D123-R123 -> 0
A124: 718/20 | B124: Joshua Rwamura | C124: Cameraperson | Q124: =E124-I124-J124-K124-L124-M124-N124-O124-P124 -> 0 | R124: =J124+K124+L124+M124+N124+O124+P124+Q124 -> 0 | S124: =D124-R124 -> 0
A125: 964/20 | B125: Joshua Wavamuno | C125: Cameraperson | Q125: =E125-I125-J125-K125-L125-M125-N125-O125-P125 -> 0 | R125: =J125+K125+L125+M125+N125+O125+P125+Q125 -> 0 | S125: =D125-R125 -> 0
... A156: 236/20 | B156: Moses Katumba | C156: Driver | Q156: =E156-I156-J156-K156-L156-M156-N156-O156-P156 -> 0 | R156: =J156+K156+L156+M156+N156+O156+P156+Q156 -> 0 | S156: =D156-R156 -> 0
A157: 237/20 | B157: Moses Namayo | Q157: =E157-I157-J157-K157-L157-M157-N157-O157-P157 -> 0 | R157: =J157+K157+L157+M157+N157+O157+P157+Q157 -> 0 | S157: =D157-R157 -> 0
A158: 037/20 | B158: Moses Oyoma | C158: Head Sales | Q158: =E158-I158-J158-K158-L158-M158-N158-O158-P158 -> 0 | R158: =J158+K158+L158+M158+N158+O158+P158+Q158 -> 0 | S158: =D158-R158 -> 0
A159: 717/20 | B159: Muhammad Mutatiina | C159: Video Journalist | Q159: =E159-I159-J159-K159-L159-M159-N159-O159-P159 -> 0 | R159: =J159+K159+L159+M159+N159+O159+P159+Q159 -> 0 | S159: =D159-R159 -> 0
A160: 233/20 | B160: Muhsin Kaliisa | C160: Cameran | Q160: =E160-I160-J160-K160-L160-M160-N160-O160-P160 -> 0 | R160: =J160+K160+L160+M160+N160+O160+P160+Q160 -> 0 | S160: =D160-R160 -> 0
A161: 242/20 | B161: Mwasit Kaudha | C161: Asst. Admin | Q161: =E161-I161-J161-K161-L161-M161-N161-O161-P161 -> 0 | R161: =J161+K161+L161+M161+N161+O161+P161+Q161 -> 0 | S161: =D161-R161 -> 0
A162: 244/20 | B162: Nelson Babyale | C162: Deputy Head of Eng news | Q162: =E162-I162-J162-K162-L162-M162-N162-O162-P162 -> 0 | R162: =J162+K162+L162+M162+N162+O162+P162+Q162 -> 0 | S162: =D162-R162 -> 0
A163: 489/20 | B163: Nina Kakwanzi | C163: Show Host | Q163: =E163-I163-J163-K163-L163-M163-N163-O163-P163 -> 0 | R163: =J163+K163+L163+M163+N163+O163+P163+Q163 -> 0 | S163: =D163-R163 -> 0
A164: 518/20 | B164: Noel Nabakka | C164: Video Editor | Q164: =E164-I164-J164-K164-L164-M164-N164-O164-P164 -> 0 | R164: =J164+K164+L164+M164+N164+O164+P164+Q164 -> 0 | S164: =D164-R164 -> 0
A165: 776/20 | B165: Oscar Mujuni Diego | C165: Sports Reporter | Q165: =E165-I165-J165-K165-L165-M165-N165-O165-P165 -> 0 | R165: =J165+K165+L165+M165+N165+O165+P165+Q165 -> 0 | S165: =D165-R165 -> 0
A166: 713/20 | B166: Patience Nakiyuka | C166: WxO | Q166: =E166-I166-J166-K166-L166-M166-N166-O166-P166 -> 0 | R166: =J166+K166+L166+M166+N166+O166+P166+Q166 -> 0 | S166: =D166-R166 -> 0
A167: 551/20 | B167: Patricia Agaba | C167: WXO | Q167: =E167-I167-J167-K167-L167-M167-N167-O167-P167 -> 0 | R167: =J167+K167+L167+M167+N167+O167+P167+Q167 -> 0 | S167: =D167-R167 -> 0
A168: 047/20 | B168: Patrick Ejobi | C168: Live Sports Producer | Q168: =E168-I168-J168-K168-L168-M168-N168-O168-P168 -> 0 | R168: =J168+K168+L168+M168+N168+O168+P168+Q168 -> 0 | S168: =D168-R168 -> 0
A169: 038/25 | B169: Patrick Masereka Makanika | C169: Bureau Reporter | Q169: =E169-I169-J169-K169-L169-M169-N169-O169-P169 -> 0 | R169: =J169+K169+L169+M169+N169+O169+P169+Q169 -> 0 | S169: =D169-R169 -> 0
B170: Patrick Obore | C170: Video Editor | Q170: =E170-I170-J170-K170-L170-M170-N170-O170-P170 -> 0 | R170: =J170+K170+L170+M170+N170+O170+P170+Q170 -> 0 | S170: =D170-R170 -> 0
A171: 258/20 | B171: Patrick Sekanjako | C171: Cleaner | Q171: =E171-I171-J171-K171-L171-M171-N171-O171-P171 -> 0 | R171: =J171+K171+L171+M171+N171+O171+P171+Q171 -> 0 | S171: =D171-R171 -> 0
A172: 680/20 | B172: Paul Aaron Odong | C172: Video Editor | Q172: =E172-I172-J172-K172-L172-M172-N172-O172-P172 -> 0 | R172: =J172+K172+L172+M172+N172+O172+P172+Q172 -> 0 | S172: =D172-R172 -> 0
A173: 067/20 | B173: Paul Kayonga | C173: News Reporter | Q173: =E173-I173-J173-K173-L173-M173-N173-O173-P173 -> 0 | R173: =J173+K173+L173+M173+N173+O173+P173+Q173 -> 0 | S173: =D173-R173 -> 0
A174: 705/20 | B174: Penninah Nyago | C174: Credit Controller | Q174: =E174-I174-J174-K174-L174-M174-N174-O174-P174 -> 0 | R174: =J174+K174+L174+M174+N174+O174+P174+Q174 -> 0 | S174: =D174-R174 -> 0
A175: 527/20 | B175: Phillip Kiwooma | C175: Transmission | Q175: =E175-I175-J175-K175-L175-M175-N175-O175-P175 -> 0 | R175: =J175+K175+L175+M175+N175+O175+P175+Q175 -> 0 | S175: =D175-R175 -> 0
A176: 931/20 | B176: Pius Enywaru | C176: Asst Quality controller | Q176: =E176-I176-J176-K176-L176-M176-N176-O176-P176 -> 0 | R176: =J176+K176+L176+M176+N176+O176+P176+Q176 -> 0 | S176: =D176-R176 -> 0
A177: 070/20 | B177: Pius Serugo | C177: Head Content production | Q177: =E177-I177-J177-K177-L177-M177-N177-O177-P177 -> 0 | R177: =J177+K177+L177+M177+N177+O177+P177+Q177 -> 0 | S177: =D177-R177 -> 0
A178: 009/20 | B178: Rachel Nyambura | C178: Chief Commercial Officer | Q178: =E178-I178-J178-K178-L178-M178-N178-O178-P178 -> 0 | R178: =J178+K178+L178+M178+N178+O178+P178+Q178 -> 0 | S178: =D178-R178 -> 0
A179: 202/25 | B179: Ramathan Kayiwa | C179: Transmission Operator | Q179: =E179-I179-J179-K179-L179-M179-N179-O179-P179 -> 0 | R179: =J179+K179+L179+M179+N179+O179+P179+Q179 -> 0 | S179: =D179-R179 -> 0
A180: 729/20 | B180: Ramson Muhaire | C180: News Reporter | Q180: =E180-I180-J180-K180-L180-M180-N180-O180-P180 -> 0 | R180: =J180+K180+L180+M180+N180+O180+P180+Q180 -> 0 | S180: =D180-R180 -> 0
A181: 998/25 | B181: Rhonet Atwiine | C181: News Reporter | Q181: =E181-I181-J181-K181-L181-M181-N181-O181-P181 -> 0 | R181: =J181+K181+L181+M181+N181+O181+P181+Q181 -> 0 | S181: =D181-R181 -> 0
A182: 724/20 | B182: Richard Kiyimba | C182: Cameraperson | Q182: =E182-I182-J182-K182-L182-M182-N182-O182-P182 -> 0 | R182: =J182+K182+L182+M182+N182+O182+P182+Q182 -> 0 | S182: =D182-R182 -> 0
... A194: 778/20 | B194: Sedrick Matsiko | C194: Facility Manager | Q194: =E194-I194-J194-K194-L194-M194-N194-O194-P194 -> 0 | R194: =J194+K194+L194+M194+N194+O194+P194+Q194 -> 0 | S194: =D194-R194 -> 0
B195: Shafik Madangu | C195: Transmission | Q195: =E195-I195-J195-K195-L195-M195-N195-O195-P195 -> 0 | R195: =J195+K195+L195+M195+N195+O195+P195+Q195 -> 0 | S195: =D195-R195 -> 0
A196: 050/25 | B196: Shakira Nakidali | C196: Audit Officer/ Events exec | Q196: =E196-I196-J196-K196-L196-M196-N196-O196-P196 -> 0 | R196: =J196+K196+L196+M196+N196+O196+P196+Q196 -> 0 | S196: =D196-R196 -> 0
A197: 529/20 | B197: Shakira Nakisekka | C197: Clerical Officer | Q197: =E197-I197-J197-K197-L197-M197-N197-O197-P197 -> 0 | R197: =J197+K197+L197+M197+N197+O197+P197+Q197 -> 0 | S197: =D197-R197 -> 0
A198: 436/20 | B198: Shamim Nabakooza | C198: News Reporter | Q198: =E198-I198-J198-K198-L198-M198-N198-O198-P198 -> 0 | R198: =J198+K198+L198+M198+N198+O198+P198+Q198 -> 0 | S198: =D198-R198 -> 0
A199: 655/20 | B199: Sherinah Nimushaba | C199: WXO | Q199: =E199-I199-J199-K199-L199-M199-N199-O199-P199 -> 0 | R199: =J199+K199+L199+M199+N199+O199+P199+Q199 -> 0 | S199: =D199-R199 -> 0
A200: 049/20 | B200: Shirly Mukunde | C200: Exec- Marketing | Q200: =E200-I200-J200-K200-L200-M200-N200-O200-P200 -> 0 | R200: =J200+K200+L200+M200+N200+O200+P200+Q200 -> 0 | S200: =D200-R200 -> 0
A201: 147/26 | B201: Simon Kisakye | C201: Head of Projects Operations | Q201: =E201-I201-J201-K201-L201-M201-N201-O201-P201 -> 0 | R201: =J201+K201+L201+M201+N201+O201+P201+Q201 -> 0 | S201: =D201-R201 -> 0
A202: 765/20 | B202: Solomon Obaet | C202: Transmission Asst | Q202: =E202-I202-J202-K202-L202-M202-N202-O202-P202 -> 0 | R202: =J202+K202+L202+M202+N202+O202+P202+Q202 -> 0 | S202: =D202-R202 -> 0
A203: 138/26 | B203: Stephen Mulinde | C203: Video Editor | Q203: =E203-I203-J203-K203-L203-M203-N203-O203-P203 -> 0 | R203: =J203+K203+L203+M203+N203+O203+P203+Q203 -> 0 | S203: =D203-R203 -> 0
A204: 076/20 | B204: Steven Musoke | C204: Head Camera | Q204: =E204-I204-J204-K204-L204-M204-N204-O204-P204 -> 0 | R204: =J204+K204+L204+M204+N204+O204+P204+Q204 -> 0 | S204: =D204-R204 -> 0
A205: 999/25 | B205: Sulaiman Ssebugwawo | C205: News Reporter | Q205: =E205-I205-J205-K205-L205-M205-N205-O205-P205 -> 0 | R205: =J205+K205+L205+M205+N205+O205+P205+Q205 -> 0 | S205: =D205-R205 -> 0
A206: 300/20 | B206: Swaliki Saali | C206: Video Editor | Q206: =E206-I206-J206-K206-L206-M206-N206-O206-P206 -> 0 | R206: =J206+K206+L206+M206+N206+O206+P206+Q206 -> 0 | S206: =D206-R206 -> 0
A207: 979/20 | B207: Sylivia Nanozi | C207: Video Editor | Q207: =E207-I207-J207-K207-L207-M207-N207-O207-P207 -> 0 | R207: =J207+K207+L207+M207+N207+O207+P207+Q207 -> 0 | S207: =D207-R207 -> 0
... A218: 314/20 | B218: Zawadi Kaliisa | C218: Treasury Manager | Q218: =E218-I218-J218-K218-L218-M218-N218-O218-P218 -> 0 | R218: =J218+K218+L218+M218+N218+O218+P218+Q218 -> 0 | S218: =D218-R218 -> 0
B219: TOTAL | Q219: =SUM(Q9:Q218) -> 0 | R219: =J219+K219+L219+M219+N219+O219+P219+Q219 -> 0 | S219: =D219-R219 -> 0
Q220: =E220-I220-J220-K220-L220-M220-N220-O220-P220 -> 0 | R220: =J220+K220+L220+M220+N220+O220+P220+Q220 -> 0 | S220: =D220-R220 -> 0
B221: NBS SPORT | Q221: =E221-I221-J221-K221-L221-M221-N221-O221-P221 -> 0 | R221: =J221+K221+L221+M221+N221+O221+P221+Q221 -> 0 | S221: =D221-R221 -> 0
A222: 087/20 | B222: Ahab Bwesigye | C222: Cameraperson | Q222: =E222-I222-J222-K222-L222-M222-N222-O222-P222 -> 0 | R222: =J222+K222+L222+M222+N222+O222+P222+Q222 -> 0 | S222: =D222-R222 -> 0
A223: 963/20 | B223: Allan Damba | C223: Content Creator | Q223: =E223-I223-J223-K223-L223-M223-N223-O223-P223 -> 0 | R223: =J223+K223+L223+M223+N223+O223+P223+Q223 -> 0 | S223: =D223-R223 -> 0
A224: 565/20 | B224: Asia Namagala | C224: Scheduller | Q224: =E224-I224-J224-K224-L224-M224-N224-O224-P224 -> 0 | R224: =J224+K224+L224+M224+N224+O224+P224+Q224 -> 0 | S224: =D224-R224 -> 0
A225: 475/20 | B225: Benjamin Jermain Egesa | C225: Show Host | Q225: =E225-I225-J225-K225-L225-M225-N225-O225-P225 -> 0 | R225: =J225+K225+L225+M225+N225+O225+P225+Q225 -> 0 | S225: =D225-R225 -> 0
A226: 553/20 | B226: Brian Tukasingura | C226: Show Host | Q226: =E226-I226-J226-K226-L226-M226-N226-O226-P226 -> 0 | R226: =J226+K226+L226+M226+N226+O226+P226+Q226 -> 0 | S226: =D226-R226 -> 0
A227: 951/20 | B227: Constant Alii | C227: Sports Producer | Q227: =E227-I227-J227-K227-L227-M227-N227-O227-P227 -> 0 | R227: =J227+K227+L227+M227+N227+O227+P227+Q227 -> 0 | S227: =D227-R227 -> 0
A228: 960/20 | B228: David Tumusiime | C228: Sports Producer | Q228: =E228-I228-J228-K228-L228-M228-N228-O228-P228 -> 0 | R228: =J228+K228+L228+M228+N228+O228+P228+Q228 -> 0 | S228: =D228-R228 -> 0
A229: 975/20 | B229: Elisha Njawuzi | C229: Driver | Q229: =E229-I229-J229-K229-L229-M229-N229-O229-P229 -> 0 | R229: =J229+K229+L229+M229+N229+O229+P229+Q229 -> 0 | S229: =D229-R229 -> 0
A230: 970/20 | B230: Ernest Akorebirungi | C230: Producer/Host | Q230: =E230-I230-J230-K230-L230-M230-N230-O230-P230 -> 0 | R230: =J230+K230+L230+M230+N230+O230+P230+Q230 -> 0 | S230: =D230-R230 -> 0
A231: 434/20 | B231: Gloria Namayanja | C231: Content | Q231: =E231-I231-J231-K231-L231-M231-N231-O231-P231 -> 0 | R231: =J231+K231+L231+M231+N231+O231+P231+Q231 -> 0 | S231: =D231-R231 -> 0
A232: 971/20 | B232: Grace Nambafu | Q232: =E232-I232-J232-K232-L232-M232-N232-O232-P232 -> 0 | R232: =J232+K232+L232+M232+N232+O232+P232+Q232 -> 0 | S232: =D232-R232 -> 0
A233: 519/20 | B233: Joseph Wamala | C233: Camera Person | Q233: =E233-I233-J233-K233-L233-M233-N233-O233-P233 -> 0 | R233: =J233+K233+L233+M233+N233+O233+P233+Q233 -> 0 | S233: =D233-R233 -> 0
A234: 517/20 | B234: Jovita Musiimenta | C234: Transmission | Q234: =E234-I234-J234-K234-L234-M234-N234-O234-P234 -> 0 | R234: =J234+K234+L234+M234+N234+O234+P234+Q234 -> 0 | S234: =D234-R234 -> 0
A235: 589/20 | B235: Justus Barongo | C235: Video Editor | Q235: =E235-I235-J235-K235-L235-M235-N235-O235-P235 -> 0 | R235: =J235+K235+L235+M235+N235+O235+P235+Q235 -> 0 | S235: =D235-R235 -> 0
A236: 224/20 | B236: Martin Kaddu | C236: Show Host | Q236: =E236-I236-J236-K236-L236-M236-N236-O236-P236 -> 0 | R236: =J236+K236+L236+M236+N236+O236+P236+Q236 -> 0 | S236: =D236-R236 -> 0
A237: 583/20 | B237: Osbert Namanya | C237: Transmission Asst | Q237: =E237-I237-J237-K237-L237-M237-N237-O237-P237 -> 0 | R237: =J237+K237+L237+M237+N237+O237+P237+Q237 -> 0 | S237: =D237-R237 -> 0
A238: 552/20 | B238: Phiona Nakatte | C238: Transmission | Q238: =E238-I238-J238-K238-L238-M238-N238-O238-P238 -> 0 | R238: =J238+K238+L238+M238+N238+O238+P238+Q238 -> 0 | S238: =D238-R238 -> 0
A239: 973/20 | B239: Samuel Ssesanga | C239: Content Creator | Q239: =E239-I239-J239-K239-L239-M239-N239-O239-P239 -> 0 | R239: =J239+K239+L239+M239+N239+O239+P239+Q239 -> 0 | S239: =D239-R239 -> 0
A240: 585/20 | B240: Sarah Nabwami | C240: Transmission Asst | Q240: =E240-I240-J240-K240-L240-M240-N240-O240-P240 -> 0 | R240: =J240+K240+L240+M240+N240+O240+P240+Q240 -> 0 | S240: =D240-R240 -> 0
A241: 682/20 | B241: Sarah Precious Yaweh | C241: Show Host/Producer | Q241: =E241-I241-J241-K241-L241-M241-N241-O241-P241 -> 0 | R241: =J241+K241+L241+M241+N241+O241+P241+Q241 -> 0 | S241: =D241-R241 -> 0
A242: 294/20 | B242: Solomon Ssaka | C242: Show Host | Q242: =E242-I242-J242-K242-L242-M242-N242-O242-P242 -> 0 | R242: =J242+K242+L242+M242+N242+O242+P242+Q242 -> 0 | S242: =D242-R242 -> 0
A243: 750/20 | B243: Victor Oloo | C243: Online Editor | Q243: =E243-I243-J243-K243-L243-M243-N243-O243-P243 -> 0 | R243: =J243+K243+L243+M243+N243+O243+P243+Q243 -> 0 | S243: =D243-R243 -> 0
A244: 458/20 | B244: Yusuf Kabenge | C244: Sports Producer | Q244: =E244-I244-J244-K244-L244-M244-N244-O244-P244 -> 0 | R244: =J244+K244+L244+M244+N244+O244+P244+Q244 -> 0 | S244: =D244-R244 -> 0
...

Sheet Bank Exp Allowance
B1: NBS
B2: S/No. | C2: Name | E2: Saving Account No. | F2: Amount
B3: 1 | C3: Kaudha Mwasit | E3: 1013011661297 | F3: =+Exp!L107 -> 0
B4: 2 | C4: Salmah Namwanje | E4: 1013011937394 | F4: =+Exp!L152 -> 0
B5: 3 | C5: Richard Olwenyi | E5: 1151152915113 | F5: =+Exp!L149 -> 0
B6: 4 | C6: Semwogerere Derick | E6: 01073044211710 | F6: =+Exp!L45 -> 0
B7: 5 | C7: Ibanda Samuel | E7: 01493014713209 | F7: =+Exp!L77 -> 0
B8: 6 | C8: Isaac Mubuka | E8: 01063089038015 | F8: =+Exp!L82 -> 0
B9: 7 | C9: Joseph Mawanda | E9: 01063089095825 | F9: =+Exp!L95 -> 0
B10: 8 | C10: Irene Constance Namajja | E10: 01063089069431 | F10: =+Exp!L133 -> 0
B11: 9 | C11: Isima Isiko | E11: 01063089037812 | F11: =+Exp!L85 -> 0
B12: 10 | C12: Katumba Moses | E12: 01513089227682 | F12: =+Exp!L106 -> 0
B13: 11 | C13: Alex Mugasha | E13: 01081157877128 | F13: =+Exp!L18 -> 0
B14: 12 | C14: Brian Tukasingura | E14: 01421000215916 | F14: =+Exp!L182 -> 0
B15: 13 | C15: Ayamo Ruth Eyobu | E15: 01081099698765 | F15: =+Exp!L24 -> 0
B16: 14 | C16: Timothy Maganda | E16: 01221151480319 | F16: =+Exp!L166 -> 0
B17: 15 | C17: Badru Kasirye | E17: 01063089284508 | F17: =+Exp!L25 -> 0
B18: 16 | C18: Kyomu Henry | E18: 1063013376621 | F18: =+Exp!L75 -> 0
B19: 18 | C19: Henry Mugenyi | E19: 01070010802519 | F19: =+Exp!L76 -> 0
B20: 19 | C20: Kitimbo Thomas | E20: 01440011974888 | F20: =+Exp!L110 -> 0
B21: 20 | C21: Kenneth Kaweesa | E21: 01060012126804 | F21: =+Exp!L108 -> 0
B22: 21 | C22: Kiwanuka John Paul | E22: 01070012330676 | F22: =+Exp!L93 -> 0
B23: 22 | C23: Magembe Farish | E23: 01030012235582 | F23: =+Exp!L56 -> 0
B24: 23 | C24: Joseph Omagor | E24: 01981131213490 | F24: =+Exp!L96 -> 0
B25: 24 | C25: Agrey Waguma | E25: 01070014050534 | F25: =+Exp!L15 -> 0
B26: 25 | C26: Wasswa Hassan Mutebi | E26: 01070010885253 | F26: =+Exp!L72 -> 0
B27: 26 | C27: Dennis Ibanda | E27: 01070014676345 | F27: =+Exp!L43 -> 0
B28: 27 | C28: Jamila Mulindwa Namuyiga | E28: 01010014546860 | F28: =+Exp!L90 -> 0
B29: 28 | C29: Paul Kayonga | E29: 01451152440673 | F29: =+Exp!L142 -> 0
B30: 29 | C30: Musisi Eric Njagala | E30: 1070011937104 | F30: =+Exp!L51 -> 0
B31: 30 | C31: Shirly Mukunde | E31: 1410014601484 | F31: =+Exp!L158 -> 0
B32: 31 | C32: Joshua Mujunga | E32: 01070014831027 | F32: =+Exp!L100 -> 0
B33: 32 | C33: Isaiah Ampumuza | E33: 01070015281562 | F33: =+Exp!L84 -> 0
B34: 33 | C34: Alex Ssentongo | E34: 227559200011 | F34: =+Exp!L19 -> 0
B35: 34 | C35: Lailah Nalukwata | E35: 0143099898523 | F35: =+Exp!L112 -> 0
B36: 35 | C36: Ahabu Bwesigye | E36: 01170015014825 | F36: =+Exp!L179 -> 0
B37: 36 | C37: Aaron Paul Odong | E37: 01490015297457 | F37: =+Exp!L141 -> 0
B38: 37 | C38: Sultan Buyungo Ahmed | E38: 01070012379118 | F38: =+Exp!L16 -> 0
B39: 38 | C39: Mark Agaba | E39: 01660011955368 | F39: =+Exp!L121 -> 0
B40: 39 | C40: Marvin Ndahura | E40: 01070015415899 | F40: =+Exp!L125 -> 0
B41: 40 | C41: Katagwa George | E41: 01070015520050 | F41: =+Exp!L105 -> 0
B42: 41 | C42: Henry Kasozi | E42: 01070010176085 | F42: =+Exp!L74 -> 0
B43: 42 | C43: Afasha Bosco | E43: 01190015807601 | F43: =+Exp!L32 -> 0
B44: 43 | C44: Victor Tayebwa | E44: 01410010961193 | F44: =+Exp!L171 -> 0
B45: 44 | C45: Richard Kiyimba | E45: 01070015481016 | F45: =+Exp!L148 -> 0
B46: 45 | C46: Abubaker Lubwama | E46: 227465200017 | F46: =+Exp!L12 -> 0
B47: 46 | C47: Joseph Rwanguhayo | E47: 01070012356607 | F47: =+Exp!L97 -> 0
B48: 47 | C48: Graham Tusiime | E48: 01070011936701 | F48: =+Exp!L68 -> 0
B49: 48 | C49: Kaddu Martin Mwogere | E49: 01170016077331 | F49: =+Exp!L192 -> 0
B50: 49 | C50: Tumusiime David | E50: 01081159107625 | F50: =+Exp!L184 -> 0
B51: 50 | C51: Adam Mayambala | E51: 01310016218499 | F51: =+Exp!L13 -> 0
B52: 51 | C52: Ramson Muhairwe | E52: 01360016344846 | F52: =+Exp!L146 -> 0
B53: 52 | C53: Goretti Kyeswa | E53: 01490016484825 | F53: =+Exp!L66 -> 0
B54: 53 | C54: Joseph Makumbi | E54: 01410015811097 | F54: =+Exp!L94 -> 0
B55: 54 | C55: Ibrahim Sserengana | E55: 01490011466185 | F55: =+Exp!L78 -> 0
B56: 55 | C56: Allan Ssempembwa | E56: 227494200013 | F56: =+Exp!L21 -> 0
B57: 56 | C57: Walugembe Josephat | E57: 1070014924514 | F57: =+Exp!L98 -> 0
B58: 57 | C58: Ernest Akorebirungi | E58: 01010016658615 | F58: =+Exp!L186 -> 0
B59: 58 | C59: Namayanja Gloria | E59: 01100016624368 | F59: =+Exp!L187 -> 0
B60: 59 | C60: Shakira Nakidali | E60: 227435200018 | F60: =+Exp!L156 -> 0
B61: 60 | C61: Julius Yiga Bakabaage | E61: 01440016690295 | F61: =+Exp!L104 -> 0
B62: 61 | C62: Sylvia Nanozi | E62: 227501200017 | F62: =+Exp!L165 -> 0
B63: 62 | C63: Lawrence Mushabe | E63: 01560016845794 | F63: =+Exp!L111 -> 0
B64: 63 | C64: Nabakooza Lydia | E64: 01060016840355 | F64: =+Exp!L117 -> 0
B65: 64 | C65: Elisha Njawuzi | E65: 01490016932319 | F65: =+Exp!L185 -> 0
B66: 65 | C66: Levi Muhoozi | E66: 01100016898042 | F66: =+Exp!L113 -> 0
B67: 66 | C67: Dan Ayebare | E67: 01490016885547 | F67: =+Exp!L41 -> 0
B68: 67 | C68: Hakiim Wampamba | E68: 01310017130318 | F68: =+Exp!L70 -> 0
B69: 68 | C69: Grace Nambafu | E69: 01250017566247 | F69: =+Exp!L188 -> 0
B70: 69 | C70: Mubiru Ivan | E70: 01310014621642 | F70: =+Exp!L87 -> 0
B71: 70 | C71: Simon Kisakye | E71: 227532200017 | F71: =+Exp!L159 -> 0
B72: 71 | C72: Mulinde Stephen | E72: 228407200018 | F72: =+Exp!L161 -> 0
B73: 72 | C73: Samson Kasumba Mulunda | E73: 6005835370 | F73: =+Exp!L153 -> 0
B74: 73 | C74: Solomon Ssaka | E74: 6006425257 | F74: =+Exp!L196 -> 0
B75: 74 | C75: Patrick Ejobi | E75: 0698164611 | F75: =+Exp!L139 -> 0
B76: 75 | C76: Ivan Rwerekana | E76: 6006735868 | F76: =+Exp!L88 -> 0
B77: 76 | C77: Robert Mwesige | E77: 6006873853 | F77: =+Exp!L151 -> 0
B78: 77 | C78: Maurice Muwonge | E78: 6007132822 | F78: =+Exp!L128 -> 0
B79: 78 | C79: William Nsimbe | E79: 6006672807 | F79: =+Exp!L174 -> 0
B80: 79 | C80: Ntege Hamza | E80: 6005849274 | F80: =+Exp!L137 -> 0
B81: 80 | C81: Justus Barongo | E81: 6007518194 | F81: =+Exp!L191 -> 0
B82: 81 | C82: Gorret Nakalinzi | E82: 01193012883443 | F82: =+Exp!L67 -> 0
B83: 82 | C83: Lotus Martha Kugonza | E83: 6006151580 | F83: =+Exp!L115 -> 0
B84: 83 | C84: Birungi Esther | E84: 6008615347 | F84: =+Exp!L53 -> 0
B85: 84 | C85: Martha Namutebi | E85: 6007644483 | F85: =+Exp!L122 -> 0
B86: 85 | C86: Sedrick Matsiko | E86: 6008741946 | F86: =+Exp!L155 -> 0
B87: 87 | C87: Aaron Magulu | E87: 6008586126 | F87: =+Exp!L8 -> 0
B88: 88 | C88: Joseph Wamala | E88: 6009824128 | F88: =+Exp!L189 -> 0
B89: 89 | C89: Shamim Nabakooza | E89: 9030017113398 | F89: =+Exp!L157 -> 0
B90: 90 | C90: Martin Okudi | E90: 9030011090671 | F90: =+Exp!L124 -> 0
B91: 91 | C91: Benjamin Egesa Osipo | E91: 9030007928873 | F91: =+Exp!L181 -> 0
B92: 92 | C92: Maclean Atuhaire | E92: 9030019911925 | F92: =+Exp!L118 -> 0
B93: 93 | C93: Yusuf Kabenge | E93: 9030015720904 | F93: =+Exp!L198 -> 0
B94: 94 | C94: Precious Sarah Yahweh | E94: 9030023625635 | F94: =+Exp!L195 -> 0
B95: 95 | C95: Abdallar Gulemye | E95: 9030016402671 | F95: =+Exp!L9 -> 0
B96: 96 | C96: Noel Nabakka | E96: 9030018341106 | F96: =+Exp!L136 -> 0
B97: 97 | C97: Victor Immanuel Oloo | E97: 9030017593802 | F97: =+Exp!L197 -> 0
B98: 98 | C98: Pius Enywaru | E98: 9030015949219 | F98: =+Exp!L144 -> 0
B99: 99 | C99: Tracy Beatrice Tendo | E99: 9030020761651 | F99: =+Exp!L168 -> 0
B100: 100 | C100: Derrick Kyambadde | E100: 9030021292248 | F100: =+Exp!L44 -> 0
...

Sheet Bank Salary
B1: NBS
B2: S/No. | C2: Name | D2: ST/REF. No. | E2: Saving Account No. | F2: Amount
B3: 1 | C3: Kaudha Mwasit | D3: 050147 | E3: 1013011661297 | F3: =+Salary!Q161 -> 0
B4: 2 | C4: Salmah Namwanje | D4: 050147 | E4: 1013011937394 | F4: =+Salary!Q190 -> 0
B5: 3 | C5: Semwogerere Derick | D5: 050147 | E5: 01073044211710 | F5: =+Salary!Q49 -> 0
B6: 4 | C6: Ibanda Samuel | D6: 050147 | E6: 01493014713209 | F6: =+Salary!Q191 -> 0
B7: 5 | C7: Richard Olwenyi | D7: 050147 | E7: 1151152915113 | F7: =+Salary!Q183 -> 0
B8: 6 | C8: Isaac Mubuka | D8: 050147 | E8: 01063089038015 | F8: =+Salary!Q99 -> 0
B9: 7 | C9: Joseph Mawanda | D9: 050147 | E9: 01063089095825 | F9: =+Salary!Q117 -> 0
B10: 8 | C10: Irene Constance Namajja | D10: 050147 | E10: 01063089069431 | F10: =+Salary!Q94 -> 0
B11: 9 | C11: Isima Isiko | D11: 050147 | E11: 01063089037812 | F11: =+Salary!Q103 -> 0
B12: 10 | C12: Katumba Moses | D12: 050147 | E12: 01513089227682 | F12: =+Salary!Q156 -> 0
B13: 11 | C13: Alex Mugasha | D13: 050147 | E13: 01081157877128 | F13: =+Salary!Q21 -> 0
B14: 12 | C14: Isaac otwii | D14: 050147 | E14: 01051154833026 | F14: =+Salary!Q100 -> 0
B15: 13 | C15: Brian Tukasingura | D15: 050147 | E15: 01421000215916 | F15: =+Salary!Q226 -> 0
B16: 14 | C16: Ayamo Ruth Eyobu | D16: 050147 | E16: 01081099698765 | F16: =+Salary!Q189 -> 0
B17: 15 | C17: Kyomu Henry | D17: 050147 | E17: 1063013376621 | F17: =+Salary!Q90 -> 0
B18: 16 | C18: Pheiona Nakatte | D18: 050147 | E18: 01490010829509 | F18: =+Salary!Q238 -> 0
B19: 17 | C19: Sarah Nabwami | D19: 050147 | E19: 01071159815335 | F19: =+Salary!Q240 -> 0
B20: 18 | C20: Henry Mugenyi | D20: 050147 | E20: 01070010802519 | F20: =+Salary!Q91 -> 0
B21: 19 | C21: Patricia Agaba | D21: 050147 | E21: 01070011977414 | F21: =+Salary!Q167 -> 0
B22: 20 | C22: Kitimbo Thomas | D22: 050147 | E22: 01440011974888 | F22: =+Salary!Q209 -> 0
B23: 21 | C23: Magembe Farish | D23: 050147 | E23: 01030012235582 | F23: =+Salary!Q65 -> 0
B24: 22 | C24: Kenneth Kaweesa | D24: 050147 | E24: 01060012126804 | F24: =+Salary!Q131 -> 0
B25: 23 | C25: Kiwanuka John Paul | D25: 050147 | E25: 01070012330676 | F25: =+Salary!Q115 -> 0
B26: 24 | C26: Simon Kaggwa Njala | D26: 050147 | E26: 01013010046204 | F26: =+Salary!Q262 -> 0
B27: 25 | C27: Joseph Omagor | D27: 050147 | E27: 01981131213490 | F27: =+Salary!Q118 -> 0
B28: 26 | C28: Agrey Waguma | D28: 050147 | E28: 01070014050534 | F28: =+Salary!Q16 -> 0
B29: 27 | C29: Wasswa Hassan Mutebi | D29: 050147 | E29: 01070010885253 | F29: =+Salary!Q87 -> 0
B30: 28 | C30: Dennis Ibanda | D30: 050147 | E30: 01070014676345 | F30: =+Salary!Q46 -> 0
B31: 29 | C31: Paul Kayonga | D31: 050147 | E31: 01451152440673 | F31: =+Salary!Q173 -> 0
B32: 30 | C32: Jamila Mulindwa Namuyiga | D32: 050147 | E32: 01010014546860 | F32: =+Salary!Q110 -> 0
B33: 31 | C33: Ssekanjako Patrick | D33: 050147 | E33: 01070012379057 | F33: =+Salary!Q171 -> 0
B34: 32 | C34: Musisi Eric Njagala | D34: 050147 | E34: 1070011937104 | F34: =+Salary!Q59 -> 0
B35: 33 | C35: Joshua Mujunga | D35: 050147 | E35: 01070014831027 | F35: =+Salary!Q123 -> 0
B36: 34 | C36: Malcom Ntambi | D36: 050147 | E36: 01070014765605 | F36: =+Salary!Q141 -> 0
B37: 35 | C37: Ahabu Bwesigye | D37: 050147 | E37: 01170015014825 | F37: =+Salary!Q222 -> 0
B38: 36 | C38: Mark Agaba | D38: 050147 | E38: 01660011955368 | F38: =+Salary!Q144 -> 0
B39: 37 | C39: Aaron Paul Odong | D39: 050147 | E39: 01490015297457 | F39: =+Salary!Q172 -> 0
B40: 38 | C40: Isaiah Ampumuza | D40: 050147 | E40: 01070015281562 | F40: =+Salary!Q102 -> 0
B41: 39 | C41: Sultan Buyungo Ahmed | D41: 050147 | E41: 01070012379118 | F41: =+Salary!Q17 -> 0
B42: 40 | C42: Alex Ssentongo | D42: 360147 | E42: 227559200011 | F42: =+Salary!Q22 -> 0
B43: 41 | C43: Andrew Batwerinde Sserwadda | D43: 050147 | E43: 1070015176424 | F43: =+Salary!Q24 -> 0
B44: 42 | C44: Marvin Ndahura | D44: 050147 | E44: 01070015415899 | F44: =+Salary!Q149 -> 0
B45: 43 | C45: Elly Makune | D45: 050147 | E45: 01660015762290 | F45: =+Salary!Q55 -> 0
B46: 44 | C46: Allan Mark Kiberu | D46: 050147 | E46: 06190015775047 | F46: =+Salary!Q20 -> 0
B47: 45 | C47: Henry Kasozi | D47: 050147 | E47: 01070010176085 | F47: =+Salary!Q89 -> 0
B48: 46 | C48: Kakande George | D48: 050147 | E48: 01070015778451 | F48: =+Salary!Q270 -> 0
B49: 47 | C49: Afasha Bosco | D49: 050147 | E49: 01190015807601 | F49: =+Salary!Q33 -> 0
B50: 48 | C50: Katagwa George | D50: 050147 | E50: 01070015520050 | F50: =+Salary!Q73 -> 0
B51: 49 | C51: Richard Kiyimba | D51: 050147 | E51: 01070015481016 | F51: =+Salary!Q182 -> 0
B52: 50 | C52: Victor Tayebwa | D52: 050147 | E52: 01410010961193 | F52: =+Salary!Q214 -> 0
B53: 51 | C53: Joseph Rwanguhayo | D53: 050147 | E53: 01070012356607 | F53: =+Salary!Q119 -> 0
B54: 52 | C54: Graham Tusiime | D54: 050147 | E54: 01070011936701 | F54: =+Salary!Q82 -> 0
B55: 53 | C55: Kaddu Martin Mwogere | D55: 050147 | E55: 01170016077331 | F55: =+Salary!Q236 -> 0
B56: 54 | C56: Tumusiime David | D56: 050147 | E56: 01081159107625 | F56: =+Salary!Q228 -> 0
B57: 55 | C57: Adam Mayambala | D57: 050147 | E57: 01310016218499 | F57: =+Salary!Q14 -> 0
B58: 56 | C58: Ramson Muhairwe | D58: 050147 | E58: 01360016344846 | F58: =+Salary!Q180 -> 0
B59: 57 | C59: Allan Ssempembwa | D59: 360147 | E59: 227494200013 | F59: =+Salary!Q23 -> 0
B60: 58 | C60: Joseph Makumbi | D60: 050147 | E60: 01410015811097 | F60: =+Salary!Q116 -> 0
B61: 59 | C61: Ronald Ekak | D61: 050147 | E61: 01660015507259 | F61: =+Salary!Q187 -> 0
B62: 60 | C62: Ibrahim Sserengana | D62: 050147 | E62: 01490011466185 | F62: =+Salary!Q92 -> 0
B63: 61 | C63: Walugembe Josephat | D63: 050147 | E63: 1070014924514 | F63: =+Salary!Q121 -> 0
B64: 62 | C64: Shakira Nakidali | D64: 360147 | E64: 227435200018 | F64: =+Salary!Q196 -> 0
B65: 63 | C65: Namayanja Gloria | D65: 050147 | E65: 01100016624368 | F65: =+Salary!Q231 -> 0
B66: 64 | C66: Ernest Akorebirungi | D66: 050147 | E66: 01010016658615 | F66: =+Salary!Q230 -> 0
B67: 65 | C67: Ssozi Edward | D67: 050147 | E67: 01351152753984 | F67: =+Salary!Q54 -> 0
B68: 66 | C68: Sylvia Nanozi | D68: 360147 | E68: 227501200017 | F68: =+Salary!Q207 -> 0
B69: 67 | C69: Shakira Nakisekka | D69: 050147 | E69: 01560016737501 | F69: =+Salary!Q197 -> 0
B70: 68 | C70: Lawrence Mushabe | D70: 050147 | E70: 01560016845794 | F70: =+Salary!Q134 -> 0
B71: 69 | C71: Judith Aber | D71: 050147 | E71: 01490016850378 | F71: =+Salary!Q128 -> 0
B72: 70 | C72: Nabakooza Lydia | D72: 050147 | E72: 01060016840355 | F72: =+Salary!Q139 -> 0
B73: 71 | C73: Mbabaali Mike | D73: 050147 | E73: 01430016901728 | F73: =+Salary!Q154 -> 0
B74: 72 | C74: Elisha Njawuzi | D74: 050147 | E74: 01490016932319 | F74: =+Salary!Q229 -> 0
B75: 73 | C75: Julius Yiga Bakabaage | D75: 050147 | E75: 01440016690295 | F75: =+Salary!Q130 -> 0
B76: 74 | C76: Levi Muhoozi | D76: 050147 | E76: 01100016898042 | F76: =+Salary!Q135 -> 0
B77: 75 | C77: Dan Ayebare | D77: 050147 | E77: 01490016885547 | F77: =+Salary!Q44 -> 0
B78: 76 | C78: Hakiim Wampamba | D78: 050147 | E78: 01310017130318 | F78: =+Salary!Q84 -> 0
B79: 77 | C79: Sherinah Nimushaba | D79: 050147 | E79: 01560017338776 | F79: =+Salary!Q199 -> 0
B80: 78 | C80: Gerald Mukisa | D80: 050147 | E80: 0110017475839 | F80: =+Salary!Q75 -> 0
B81: 79 | C81: Grace Nambafu | D81: 050147 | E81: 01250017566247 | F81: =+Salary!Q232 -> 0
B82: 80 | C82: Komugisha Aisha | D82: 050147 | E82: 01410010976715 | F82: =+Salary!Q18 -> 0
B83: 81 | C83: Isaac Kuteesa | D83: 050147 | E83: 01490018034714 | F83: =+Salary!Q97 -> 0
B84: 82 | C84: Ramathan Kayiwa | D84: 360147 | E84: 227492200017 | F84: =+Salary!Q179 -> 0
B85: 83 | C85: Eddy Enuru | D85: 050147 | E85: 01550018797459 | F85: =+Salary!Q52 -> 0
B86: 84 | C86: Mubiru Ivan | D86: 050147 | E86: 01310014621642 | F86: =+Salary!Q106 -> 0
B87: 85 | C87: Simon Kisakye | D87: 360147 | E87: 227532200017 | F87: =+Salary!Q201 -> 0
B88: 86 | C88: Mulinde Stephen | D88: 360147 | E88: 228407200018 | F88: =+Salary!Q203 -> 0
B89: 87 | C89: Samson Kasumba Mulunda | D89: 013847 | E89: 6005835370 | F89: =+Salary!Q192 -> 0
B90: 88 | C90: Ivan Rwerekana | D90: 013847 | E90: 6006735868 | F90: =+Salary!Q107 -> 0
B91: 89 | C91: Robert Mwesige | D91: 013847 | E91: 6006873853 | F91: =+Salary!Q185 -> 0
B92: 90 | C92: Maurice Muwonge | D92: 013847 | E92: 6007132822 | F92: =+Salary!Q152 -> 0
B93: 91 | C93: William Nsimbe | D93: 013847 | E93: 6006672807 | F93: =+Salary!Q216 -> 0
B94: 92 | C94: Ntege Hamza | D94: 013847 | E94: 6005849274 | F94: =+Salary!Q85 -> 0
B95: 93 | C95: Justus Barongo | D95: 013847 | E95: 6007518194 | F95: =+Salary!Q235 -> 0
B96: 94 | C96: Gorret Nakalinzi | D96: 050147 | E96: 01193012883443 | F96: =+Salary!Q80 -> 0
B97: 95 | C97: Lotus Martha Kugonza | D97: 013847 | E97: 6006151580 | F97: =+Salary!Q137 -> 0
B98: 96 | C98: Birungi Esther | D98: 013847 | E98: 6008615347 | F98: =+Salary!Q62 -> 0
B99: 97 | C99: Martha Namutebi | D99: 013847 | E99: 6007644483 | F99: =+Salary!Q145 -> 0
B100: 98 | C100: Aaron Magulu | D100: 013847 | E100: 6008586126 | F100: =+Salary!Q9 -> 0
...
